sentinelsat/__init__.py
sentinelsat/__main__.py
sentinelsat/download.py
sentinelsat/exceptions.py
sentinelsat/products.py
sentinelsat/sentinel.py
sentinelsat/scripts/__init__.py
sentinelsat/scripts/cli.py
sentinelsat-1.2.1.dist-info/AUTHORS.rst
sentinelsat-1.2.1.dist-info/LICENSE
sentinelsat-1.2.1.dist-info/METADATA
sentinelsat-1.2.1.dist-info/WHEEL
sentinelsat-1.2.1.dist-info/entry_points.txt
sentinelsat-1.2.1.dist-info/top_level.txt
sentinelsat-1.2.1.dist-info/zip-safe
sentinelsat-1.2.1.dist-info/RECORD
