Metadata-Version: 2.1
Name: sentinelsat
Version: 1.2.1
Summary: Utility to search and download Copernicus Sentinel satellite images
Home-page: https://github.com/sentinelsat/sentinelsat
Author: Kersten Clauss
Author-email: sentinelsat@krstn.eu
License: GPLv3+
Keywords: copernicus,sentinel,esa,satellite,download,GIS
Classifier: License :: OSI Approved :: GNU General Public License v3 or later (GPLv3+)
Classifier: Programming Language :: Python :: 3
Classifier: Programming Language :: Python :: 3.6
Classifier: Programming Language :: Python :: 3.7
Classifier: Programming Language :: Python :: 3.8
Classifier: Programming Language :: Python :: 3.9
Classifier: Programming Language :: Python :: 3.10
Classifier: Programming Language :: Python :: 3.11
Classifier: Topic :: Scientific/Engineering :: GIS
Classifier: Topic :: Utilities
Provides-Extra: dev
License-File: LICENSE
License-File: AUTHORS.rst
